shell_scripting/__init__.py
shell_scripting-0.0.2.dist-info/METADATA
shell_scripting-0.0.2.dist-info/WHEEL
shell_scripting-0.0.2.dist-info/top_level.txt
shell_scripting-0.0.2.dist-info/RECORD
