Metadata-Version: 2.1
Name: shell-scripting
Version: 0.0.2
Summary: Shortcut functions for shell scripting on Python 3.7+
Home-page: https://bitbucket.org/whoizit/shell-scripting
Author: whoami
Author-email: whoami@systemli.org
License: UNLICENSE
Platform: UNKNOWN
Classifier: Programming Language :: Python :: 3.7
Classifier: License :: Public Domain
Classifier: Operating System :: OS Independent
